[
  {
    "provider": "QuickBooks",
    "description": "Sync a QuickBooks company with a RoboLedger company to automatically import your transactions and leverage automation tools improve your accounting reporting processes.",
    "image": "/images/qb_connect.png",
    "connectionUrl": "/api/qb/auth"
  },
  {
    "provider": "SEC.gov",
    "description": "Pull in XBRL filings from SEC.gov into RoboLedger to import historical filings.",
    "image": "/images/sec_connect.png",
    "connectionUrl": "/api/sec/auth"
  },
  {
    "provider": "Plaid",
    "description": "Connect your bank accounts to automatically import transactions and account balances for real-time financial reporting and analysis.",
    "image": null,
    "connectionUrl": "/api/plaid/auth"
  }
]
